{"id":"73021418","premium":false,"billing_type":{"id":"standard","name":"Стандарт"},"relations":[],"name":"Layout Designer / HTML CSS Developer","insider_interview":null,"response_letter_required":false,"area":{"id":"236","name":"Кипр","url":"https://api.hh.ru/areas/236?host=hh.ru"},"salary":null,"type":{"id":"open","name":"Открытая"},"address":null,"allow_messages":true,"experience":{"id":"between3And6","name":"От 3 до 6 лет"},"schedule":{"id":"fullDay","name":"Полный день"},"employment":{"id":"full","name":"Полная занятость"},"department":null,"contacts":null,"description":"<p>We invite a <strong>Layout Designer/Front-end Developer</strong> (HTML, CSS, JS), with work experience of no less than two years, to join the website support and development team in the Marketing department.</p> <p><strong>Responsibilities:</strong></p> <ul> <li>Website support on custom CMS: page and block layout, optimisation and editing of the existing layout (HTML, CSS, JavaScript, jQuery)</li> <li>Blog support on WordPress: theme layout, editing, and optimisation, work with plugins/shortcodes/widgets (WordPress, PHP, JavaScript)</li> <li>Layout of regular emails. It is vital that you have experience in email layout, know the details of table layout, and the peculiarities of postal customers</li> <li>Landing layout, adding components on pages</li> <li>Adding to and downloading data from CMS</li> <li>Adding new information to websites</li> </ul> <p> </p> <p><strong>Requirements:</strong></p> <ul> <li>Be capable of finding various ways of solving a problem</li> <li>Refactor, delete unnecessary data, proactively prepare solutions for the future, keep an eye on the accuracy of projects</li> <li>Find comfortable instruments, deal with documentation</li> <li>English proficiency (speaking and writing) is required for understanding documentation, correct naming of classes and variables, making comments, etc.</li> <li>Get to the core of the situation independently, ask questions without hesitation, discuss solutions, and come to agreements</li> <li>Work on tasks that have no direct connection to active development</li> <li>Work with codes written by other people, sticking to the style</li> </ul> <p><strong>Technical stack:</strong></p> <ul> <li>Excellent knowledge of HTML, CSS</li> <li>Advanced knowledge of JavaScript, jQuery</li> <li>Confident knowledge of WordPress (work in panel, themes)</li> <li>Good knowledge of Git</li> <li>Experience in React, Vue</li> </ul> <p><strong>Will be a advantage:</strong></p> <ul> <li>Understanding of project assembly on Gulp</li> <li>Basic knowledge of PHP and Twig</li> <li>General understanding of work with Docker</li> <li>Knowing various ways of deploying a server</li> </ul> <p><strong>We offer:</strong></p> <ul> <li>Attractive monthly salary paid in line with your skills and experience</li> <li>A comfortable office in the center of Limassol (Cyprus)</li> <li>Medical insurance for our employees and their families</li> <li>Access to professional training, conferences, and paid educational courses</li> <li>Corporate language courses</li> <li>Evening yoga classes in office relaxation space</li> <li>Subsidized lunches</li> <li>Different corporate events for employees and their children</li> <li>Sports events</li> <li>Assistance in relocation and visa processing (if necessary)</li> </ul> <p> </p>","branded_description":null,"vacancy_constructor_template":null,"key_skills":[{"name":"JavaScript"},{"name":"Git"},{"name":"jQuery"},{"name":"Less"},{"name":"HTML5"},{"name":"CMS Wordpress"},{"name":"CSS"},{"name":"CSS3"}],"accept_handicapped":false,"accept_kids":false,"archived":false,"response_url":null,"specializations":[{"id":"1.221","name":"Программирование, Разработка","profarea_id":"1","profarea_name":"Информационные технологии, интернет, телеком"},{"id":"1.50","name":"Системы управления предприятием (ERP)","profarea_id":"1","profarea_name":"Информационные технологии, интернет, телеком"},{"id":"1.82","name":"Инженер","profarea_id":"1","profarea_name":"Информационные технологии, интернет, телеком"},{"id":"1.9","name":"Web инженер","profarea_id":"1","profarea_name":"Информационные технологии, интернет, телеком"},{"id":"1.10","name":"Web мастер","profarea_id":"1","profarea_name":"Информационные технологии, интернет, телеком"}],"professional_roles":[{"id":"96","name":"Программист, разработчик"}],"code":null,"hidden":false,"quick_responses_allowed":false,"driver_license_types":[],"accept_incomplete_resumes":false,"employer":{"id":"4671066","name":"RoboGate","url":"https://api.hh.ru/employers/4671066?host=hh.ru","alternate_url":"https://hh.ru/employer/4671066","logo_urls":{"original":"https://hhcdn.ru/employer-logo-original/1005282.png","90":"https://hhcdn.ru/employer-logo/5641908.png","240":"https://hhcdn.ru/employer-logo/5641909.png"},"vacancies_url":"https://api.hh.ru/vacancies?employer_id=4671066&host=hh.ru","trusted":true},"published_at":"2022-11-28T12:14:19+0300","created_at":"2022-11-28T12:14:19+0300","initial_created_at":"2022-11-28T12:14:19+0300","negotiations_url":null,"suitable_resumes_url":null,"apply_alternate_url":"https://hh.ru/applicant/vacancy_response?vacancyId=73021418","has_test":false,"test":null,"alternate_url":"https://hh.ru/vacancy/73021418","working_days":[],"working_time_intervals":[],"working_time_modes":[],"accept_temporary":false,"languages":[]}