{"id":"74192407","premium":false,"billing_type":{"id":"standard","name":"Стандарт"},"relations":[],"name":"Senior Android Developer","insider_interview":null,"response_letter_required":false,"area":{"id":"236","name":"Кипр","url":"https://api.hh.ru/areas/236?host=hh.ru"},"salary":null,"type":{"id":"open","name":"Открытая"},"address":{"city":"City of Limassol","street":null,"building":null,"description":null,"lat":34.687014,"lng":33.036281,"raw":"City of Limassol","metro":null,"metro_stations":[]},"allow_messages":true,"experience":{"id":"between3And6","name":"От 3 до 6 лет"},"schedule":{"id":"fullDay","name":"Полный день"},"employment":{"id":"full","name":"Полная занятость"},"department":null,"contacts":null,"description":"<p>ToYou is a leading online Saudi food ordering and delivery super-app with one of the largest and most comprehensive networks of merchants across the Kingdom of Saudi Arabia. We seek to deliver all necessities across the Kingdom, whether they be from restaurants, supermarkets, pharmacies, or more.</p> <p>At ToYou we aim to provide all our customers with a great experience by connecting them with thousands of merchants across Saudi Arabia, and we take great pride in our diverse team which represents different backgrounds, experiences, and visions. We truly value them and count them as a key factor to our success. So, if you are interested in joining a team full of intelligence, ambition, and great talent, ToYou is the right place for you.</p> <p>The successful candidate will be responsible for driving successful delivery of your work and the work of the immediate team, identifying then subsequently helping to drive efforts to mature team practices and improve the native digital platform.</p> <p>This role requires an effective technical collaborator who has core Android development expertise, has built and deployed apps to the PlayStore, and has the experience and desire to operate in a senior capacity in the Android engineering team.</p> <p><strong>Relocation to Cyprus or remote work could be considered. </strong></p> <p><strong>What the role will involve:</strong></p> <ul> <li>Designing, debugging, building and shipping Android solutions.</li> <li>To deliver Android components or application enhancements and features.</li> <li>Collaborating with stakeholders to understand task scope and solidify requirements.</li> <li>Clearly communicating the engineering development perspective and discussing complex topics with technical and non-technical team members.</li> <li>Defining and upholding standards for quality through constructive code reviews, fixing bugs, writing tests, and good coding practices.</li> <li>Build new user-facing features and help drive mobile product strategy.</li> <li>Create tools and infrastructure to enable rapid iteration cycles on mobile.</li> </ul> <p><strong>Role Responsibilities:</strong></p> <ul> <li>Design and build customer-facing apps for the Android platform.</li> <li>Architect modular, reusable code.</li> <li>Collaborate with the product team to define, design, and ship new features.</li> <li>Write clean code and comprehensive tests.</li> <li>Work with outside data sources and APIs.</li> <li>Work on bug fixing and improving app performance.</li> <li>Continuously discover, evaluate, and implement new technology.</li> <li>Collaborate with other product teams to enhance mobile user experience.</li> </ul> <p><strong>Qualifications:</strong></p> <ul> <li>3+ yrs. of experience in Android application development.</li> <li>Deep understanding of Android SDK.</li> <li>Strong understanding of Kotlin and the Android development environment, including Android Studio and the Gradle build system.</li> <li>Knowledge of OOP principles, design patterns, SOLID, Clean Architecture, MVVM, MVP and MVI.</li> <li>Strong desire to write high quality, clean &amp; testable code TDD, BDD.</li> <li>Knowledge of data storage mechanisms SQLite, Room.</li> <li>Experience with Dagger 2/Hilt/Koin, Coroutines.</li> <li>Experience with custom views and animations.</li> <li>Practical experience with third party libraries Retrofit, OkHttp, Glide, etc.</li> <li>Current on modern Android development, including use of AAC, RxJava/Coroutines, Jetpack etc.</li> <li>Extensive experience developing applications leveraging remote XML/JSON data accessed via RESTful web services.</li> <li>Knowledge of SSL/TLS protocols and certificates.</li> <li>Experience working on Android applications that span a wide variety of sizes, Android OS versions, and display densities.</li> <li>Fluency in English both verbal and written.</li> </ul> <p><strong>Additional competencies:</strong></p> <ul> <li>High level of interest to current software development trends.</li> </ul> <ul> <li>Absolute attention to detail to accurately implement custom designs that scale to any screen size and form factor.</li> </ul> <p><strong>What we offer:</strong></p> <ul> <li>An attractive remuneration package.</li> <li>Medical insurance upon completion of the probation period.</li> <li>Fruits, coffee, tea, biscuits in the office.</li> <li>Contemporary work environment.</li> <li>Flexible working scheme (hybrid model).</li> <li>Ping pong table in the office.</li> </ul> <p><em><strong>Interested applicants can submit their CV in English. </strong></em></p> <p> </p> <p> </p> <ul> </ul>","branded_description":null,"vacancy_constructor_template":null,"key_skills":[{"name":"Kotlin"},{"name":"Android"},{"name":"Java"}],"accept_handicapped":false,"accept_kids":false,"archived":false,"response_url":null,"specializations":[{"id":"1.221","name":"Программирование, Разработка","profarea_id":"1","profarea_name":"Информационные технологии, интернет, телеком"},{"id":"1.50","name":"Системы управления предприятием (ERP)","profarea_id":"1","profarea_name":"Информационные технологии, интернет, телеком"},{"id":"1.82","name":"Инженер","profarea_id":"1","profarea_name":"Информационные технологии, интернет, телеком"},{"id":"1.9","name":"Web инженер","profarea_id":"1","profarea_name":"Информационные технологии, интернет, телеком"},{"id":"1.10","name":"Web мастер","profarea_id":"1","profarea_name":"Информационные технологии, интернет, телеком"}],"professional_roles":[{"id":"96","name":"Программист, разработчик"}],"code":null,"hidden":false,"quick_responses_allowed":false,"driver_license_types":[],"accept_incomplete_resumes":false,"employer":{"id":"5370841","name":"Aram Meem Services","url":"https://api.hh.ru/employers/5370841?host=hh.ru","alternate_url":"https://hh.ru/employer/5370841","logo_urls":{"90":"https://hhcdn.ru/employer-logo/3904651.png","240":"https://hhcdn.ru/employer-logo/3904652.png","original":"https://hhcdn.ru/employer-logo-original/865944.png"},"vacancies_url":"https://api.hh.ru/vacancies?employer_id=5370841&host=hh.ru","trusted":true},"published_at":"2022-12-23T17:45:48+0300","created_at":"2022-12-23T17:45:48+0300","initial_created_at":"2022-12-23T17:45:48+0300","negotiations_url":null,"suitable_resumes_url":null,"apply_alternate_url":"https://hh.ru/applicant/vacancy_response?vacancyId=74192407","has_test":false,"test":null,"alternate_url":"https://hh.ru/vacancy/74192407","working_days":[],"working_time_intervals":[],"working_time_modes":[],"accept_temporary":false,"languages":[{"id":"eng","name":"Английский","level":{"id":"b2","name":"B2 — Средне-продвинутый"}}]}