{"id":"73910659","premium":false,"billing_type":{"id":"standard","name":"Стандарт"},"relations":[],"name":"Senior Backend developer","insider_interview":null,"response_letter_required":false,"area":{"id":"43","name":"Калуга","url":"https://api.hh.ru/areas/43?host=hh.ru"},"salary":null,"type":{"id":"open","name":"Открытая"},"address":null,"allow_messages":true,"experience":{"id":"moreThan6","name":"Более 6 лет"},"schedule":{"id":"fullDay","name":"Полный день"},"employment":{"id":"full","name":"Полная занятость"},"department":null,"contacts":null,"description":"<p><strong><em>АО РТИ - компания, выполняющая масштабные стратегические задачи. Нам доверяют сложнейшие IT задачи для обеспечения национальной безопасности. Наши продукты используют десятки тысяч пользователей ежедневно.</em></strong></p> <p><strong><em>Мы объединили команды молодых и опытных профессионалов в нескольких городах для решения масштабных задач с использованием самых передовых технологий.</em></strong></p> <p><strong>Мы растем и ищем к себе в команду Senior Разработчиков</strong></p> <p><strong>Работа с нами — это:</strong></p> <ul> <li> <p>Проекты разрабатываемые на платформах .NET Core 3.1 - 6.0 / Python 3.6- 3.9 с контейнеризацией в Docker;</p> </li> <li> <p>Сервисы проектируются с расчетом на высокую нагрузку, отказоустойчивость и возможности гибкого вертикального и горизонтального масштабирования;</p> </li> <li> <p>Использование микросервисной архитектуры; Работа с инструментами RabbitMQ, Kafka, СУБД PostgreSQL, Redis, применение оркестратора Kubernetes;</p> </li> <li> <p>ORM SQLAlchemy / Entity Framework;</p> </li> <li> <p>Полностью автоматизированные процессы CI/CD, gitlab CI, Ansible;</p> </li> <li> <p>Используем методологии разработки agile и waterfall;</p> </li> <li> <p>Возможности профессионального развития: мы организуем онлайн и офлайн митапы на актуальные темы, внутренние технические и архитектурные встречи по обмену опытом.</p> </li> </ul> <p><strong>Мы ожидаем, что вы имеете:</strong></p> <ul> <li> <p>Хорошие теоретическими и практическими знаниями C# / Python (Django/Flask/Pyramid);</p> </li> <li> <p>Опыт реализации сервисов с REST API;</p> </li> <li> <p>Опыт работы с асинхронкой (aiohttp и asyncio);</p> </li> <li> <p>Опыт разработки и проектирования backend-сервисов;</p> </li> <li> <p>Знание основных архитектурных подходов и принципов;</p> </li> <li> <p>Знание SQL и основы работы СУБД;</p> </li> <li> <p>Интерес к развитию платформы .NET и смежных технологий.</p> </li> </ul> <p><strong>Плюсом будет:</strong></p> <ul> <li> <p>Наличие собственных проектов и участие в open-source проектах;</p> </li> <li> <p>Опыт проектирования масштабируемых высоконагруженных систем;</p> </li> <li> <p>Опыт работы с криптографией;</p> </li> <li> <p>Работали над большими проектами;</p> </li> <li> <p>Имеете работы с websocket&#39;ами.</p> </li> </ul> <p><strong>Наши преимущества:</strong></p> <ul> <li> <p>Официальное трудоустройство и полностью белая заработная плата на уровне рынка (обсуждается с успешными кандидатами индивидуально);</p> </li> <li> <p>ДМС со стоматологией;</p> </li> <li> <p>Ежемесячные и проектные премии по результатам работы;</p> </li> <li> <p>Повышение квалификации и обучение на курсах;</p> </li> <li> <p>Активное корпоративная жизнь (локальные митапы, программа менторства и др.);</p> </li> <li> <p>Работа в офисе в Калуге;</p> </li> <li> <p>У нас вас ждет: чай, кофе, фрукты и печеньки, возможность поиграть в настольный теннис в перерывах от работы, а также доброжелательные коллеги и понимающее руководство.</p> </li> </ul> <p><strong>УСЛОВИЯ:</strong></p> <ul> <li> <p>Итоговая зарплата по результатам собеседования;</p> </li> <li> <p>Официальное оформление, выплата зарплаты — 2 раза в месяц;</p> </li> <li> <p>Возможность удаленной работы в гибридном формате.</p> </li> </ul>","branded_description":null,"vacancy_constructor_template":null,"key_skills":[{"name":"Python"},{"name":"PostgreSQL"},{"name":"RabbitMQ"},{"name":"Redis"},{"name":"aiohttp"},{"name":"CI/CD"},{"name":"C#"},{"name":".NET Core"},{"name":".NET Framework"},{"name":"Django Framework"},{"name":"Docker"},{"name":"Django"},{"name":"SQLAlchemy"},{"name":"Kubernetes"}],"accept_handicapped":false,"accept_kids":false,"archived":false,"response_url":null,"specializations":[{"id":"12.92","name":"Информационные технологии","profarea_id":"12","profarea_name":"Консультирование"},{"id":"1.327","name":"Управление проектами","profarea_id":"1","profarea_name":"Информационные технологии, интернет, телеком"}],"professional_roles":[{"id":"104","name":"Руководитель группы разработки"}],"code":null,"hidden":false,"quick_responses_allowed":false,"driver_license_types":[],"accept_incomplete_resumes":false,"employer":{"id":"103944","name":"К-ТЕХНОЛОГИИ","url":"https://api.hh.ru/employers/103944?host=hh.ru","alternate_url":"https://hh.ru/employer/103944","logo_urls":{"240":"https://hhcdn.ru/employer-logo/5565289.png","90":"https://hhcdn.ru/employer-logo/5565288.png","original":"https://hhcdn.ru/employer-logo-original/986119.png"},"vacancies_url":"https://api.hh.ru/vacancies?employer_id=103944&host=hh.ru","trusted":true},"published_at":"2022-12-16T17:15:06+0300","created_at":"2022-12-16T17:15:06+0300","initial_created_at":"2022-12-16T17:15:06+0300","negotiations_url":null,"suitable_resumes_url":null,"apply_alternate_url":"https://hh.ru/applicant/vacancy_response?vacancyId=73910659","has_test":false,"test":null,"alternate_url":"https://hh.ru/vacancy/73910659","working_days":[],"working_time_intervals":[],"working_time_modes":[],"accept_temporary":false,"languages":[{"id":"eng","name":"Английский","level":{"id":"a1","name":"A1 — Начальный"}}]}