{"id":"70419571","premium":false,"billing_type":{"id":"standard","name":"Стандарт"},"relations":[],"name":"Инженер-программист","insider_interview":null,"response_letter_required":false,"area":{"id":"2","name":"Санкт-Петербург","url":"https://api.hh.ru/areas/2?host=hh.ru"},"salary":{"from":55000,"to":null,"currency":"RUR","gross":false},"type":{"id":"open","name":"Открытая"},"address":{"city":"Санкт-Петербург","street":"улица Пилотов","building":"12","description":null,"lat":59.810378,"lng":30.304406,"raw":"Санкт-Петербург, улица Пилотов, 12","metro":{"station_name":"Московская","line_name":"Московско-Петроградская","station_id":"15.224","line_id":"15","lat":59.848873,"lng":30.321483},"metro_stations":[{"station_name":"Московская","line_name":"Московско-Петроградская","station_id":"15.224","line_id":"15","lat":59.848873,"lng":30.321483}]},"allow_messages":true,"experience":{"id":"between1And3","name":"От 1 года до 3 лет"},"schedule":{"id":"fullDay","name":"Полный день"},"employment":{"id":"full","name":"Полная занятость"},"department":null,"contacts":null,"description":"<p><strong>Компьютерные навыки</strong>: Python, C# (предпочтительнее).</p> <p><strong>Знание иностранных языков</strong>: Английский B2</p> <p><strong>Профессиональные навыки:</strong></p> <ol> <li>Опыт разработки десктоп-приложений и программ на C# (предпочтительнее) или Python.</li> <li>Опыт работы с библиотеками обработки изображений и видео.</li> <li>Опыт работы c модулями iMX6 (Somlabs), iMX8 (Variscite), Raspberry P будет преимуществом.</li> <li>Опыт работы в Xamarin будет преимуществом.</li> </ol> <p><strong>Должностные обязанности:</strong></p> <ol> <li>Разработка, тестирование и сопровождение программного обеспечения.</li> <li>Отладка программного обеспечения.</li> <li>Защита разрабатываемого программного обеспечения.</li> <li>Подбор необходимого оборудования. <p> </p> </li> </ol> <p><strong>Условия:</strong></p> <ul> <li>Оформление в соответствии с трудовым законодательством РФ;</li> <li>Предоставляется отсрочка от призыва на военную службу по мобилизации;</li> <li>График работы 5/2 с 8:00 до 17:00, пт. с 8:00 до 15:45, в т.ч. обед 45 минут (может быть изменен по договоренности);</li> <li>Дополнительные премии по итогам работы;</li> <li>Дополнительные выплаты к государственным праздникам (8 марта, 23 февраля, Новый год);</li> <li>Частичная компенсация расходов на медицинское обслуживание;</li> <li>Ежегодный оплачиваемый отпуск 31 календарный день;</li> <li>Бесплатная развозка от станции метро &quot;Московская&quot;;</li> <li>Подарки сотрудникам на дни рождения и подарочные наборы для детей к Новому году;</li> <li>Столовая на территории предприятия;</li> <li>Заработная плата уточняется по результатам собеседования.</li> </ul>","branded_description":null,"vacancy_constructor_template":null,"key_skills":[{"name":"Английский язык"},{"name":"Python"},{"name":"Adobe Photoshop"},{"name":"C#"}],"accept_handicapped":false,"accept_kids":false,"archived":false,"response_url":null,"specializations":[{"id":"1.221","name":"Программирование, Разработка","profarea_id":"1","profarea_name":"Информационные технологии, интернет, телеком"},{"id":"1.50","name":"Системы управления предприятием (ERP)","profarea_id":"1","profarea_name":"Информационные технологии, интернет, телеком"},{"id":"1.82","name":"Инженер","profarea_id":"1","profarea_name":"Информационные технологии, интернет, телеком"},{"id":"1.9","name":"Web инженер","profarea_id":"1","profarea_name":"Информационные технологии, интернет, телеком"},{"id":"1.10","name":"Web мастер","profarea_id":"1","profarea_name":"Информационные технологии, интернет, телеком"}],"professional_roles":[{"id":"96","name":"Программист, разработчик"}],"code":null,"hidden":false,"quick_responses_allowed":false,"driver_license_types":[],"accept_incomplete_resumes":false,"employer":{"id":"463857","name":"НПО СПАРК","url":"https://api.hh.ru/employers/463857?host=hh.ru","alternate_url":"https://hh.ru/employer/463857","logo_urls":{"90":"https://hhcdn.ru/employer-logo/358507.png","240":"https://hhcdn.ru/employer-logo/431364.png","original":"https://hhcdn.ru/employer-logo-original/181895.gif"},"vacancies_url":"https://api.hh.ru/vacancies?employer_id=463857&host=hh.ru","trusted":true},"published_at":"2022-12-22T16:49:37+0300","created_at":"2022-12-22T16:49:37+0300","initial_created_at":"2022-09-27T15:28:31+0300","negotiations_url":null,"suitable_resumes_url":null,"apply_alternate_url":"https://hh.ru/applicant/vacancy_response?vacancyId=70419571","has_test":false,"test":null,"alternate_url":"https://hh.ru/vacancy/70419571","working_days":[],"working_time_intervals":[],"working_time_modes":[],"accept_temporary":false,"languages":[]}