{"id":"73097189","premium":false,"billing_type":{"id":"standard_plus","name":"Стандарт плюс"},"relations":[],"name":"Разработчик интерфейсов (Программист на QT/PyQT)","insider_interview":null,"response_letter_required":false,"area":{"id":"1","name":"Москва","url":"https://api.hh.ru/areas/1?host=hh.ru"},"salary":{"from":150000,"to":220000,"currency":"RUR","gross":true},"type":{"id":"open","name":"Открытая"},"address":null,"allow_messages":true,"experience":{"id":"between3And6","name":"От 3 до 6 лет"},"schedule":{"id":"fullDay","name":"Полный день"},"employment":{"id":"full","name":"Полная занятость"},"department":null,"contacts":null,"description":"<p>Подразделение искусственного интеллекта и анализа данных ищет новых сотрудников для участия в новых амбициозных проектах.</p> <p>Мы практически с самых истоков занимаемся AI и глубоким обучением, выполняем проекты по анализу данных, биометрии, видеоаналитике, робототехнике, основанные на разработке и обучении архитектур нейронных сетей. Наше подразделение является основным разработчиком нейросетевых решений как для крупнейших коммерческих, так и для государственных заказчиков.</p> <p>Мы ищем руководителя группы и одновременно разработчика интерфейсов клиент-серверных решений для участия в крупном проекте по разработке отечественного программного продукта для обучения нейронных сетей работающих с изображениями, голосом и другими цифровыми данными.</p> <p><strong>Цели:</strong></p> <ol> <li>Создание современных интерфейсов для разрабатываемого программного обеспечения</li> <li>Обеспечение кросс-платформенной совместимости интерфейсов</li> <li>Обеспечение usability</li> </ol> <p><strong>Обязанности:</strong></p> <ul> <li>Руководство группой разработчиков</li> <li>Участие в разработке и испытаниях ПО</li> <li>Разработка графических приложений с использованием специализированного инструментария QT/PyQT</li> <li>Профилирование, оптимизация производительности и использования ресурсов</li> <li>Документирование кода и создание технической документации.</li> <li>Работа в команде</li> </ul> <p><br /><strong>Требования:</strong></p> <ul> <li>Практический опыт использования инструментария QT (непосредственное участие в коллективных проектах в качестве разработчика). Готовность показать примеры/скриншоты разработанных приложений.</li> <li>Знание QT Creator</li> <li>Знание Python (опыт работы от 2х лет). Понимание принципов ООП</li> <li>Опыт работы с PyQT5</li> <li>Опыт работы в *nix-подобных системах</li> <li>Умение работать в команде с применением систем контроля версий</li> <li>Ответственность и работоспособность</li> </ul> <p> </p> <p><strong>Плюсом является:</strong></p> <ul> <li>Навык разработки эргономичных интерфейсов</li> <li>Опыт использования Matplotlib</li> <li>Опыт разработки GUI на Qt с использованием C++</li> <li>Опыт работы с распределенными системами, REST API, сокетами и т.п.</li> <li>Опыт работы с базами данных</li> <li>Технический английский</li> </ul> <p><strong>Условия:</strong></p> <ul> <li>Оформление согласно ТК РФ</li> <li>Офис рядом с м. Аэропорт</li> <li>График работы 5/2</li> <li>Небольшой коллектив, минимум бюрократии, максимум работы</li> <li>Конкурентная заработная плата (определяется индивидуально по итогам собеседования)</li> <li>ДМС, столовая с вкусной едой, спортзал. Возможность устроить детей в детский сад</li> <li>отсрочка от мобилизации</li> </ul>","branded_description":null,"vacancy_constructor_template":null,"key_skills":[{"name":"Qt"},{"name":"C++"},{"name":"Linux"},{"name":"ООП"},{"name":"Python"},{"name":"PyQT"},{"name":"Matplotlib"}],"accept_handicapped":false,"accept_kids":false,"archived":false,"response_url":null,"specializations":[{"id":"12.92","name":"Информационные технологии","profarea_id":"12","profarea_name":"Консультирование"},{"id":"1.327","name":"Управление проектами","profarea_id":"1","profarea_name":"Информационные технологии, интернет, телеком"}],"professional_roles":[{"id":"104","name":"Руководитель группы разработки"}],"code":null,"hidden":false,"quick_responses_allowed":false,"driver_license_types":[],"accept_incomplete_resumes":false,"employer":{"id":"1626408","name":"Федеральное автономное учреждение Государственный Научно-Исследовательский Институт Авиационных Систем","url":"https://api.hh.ru/employers/1626408?host=hh.ru","alternate_url":"https://hh.ru/employer/1626408","logo_urls":{"original":"https://hhcdn.ru/employer-logo-original/238329.png","90":"https://hhcdn.ru/employer-logo/1395993.png","240":"https://hhcdn.ru/employer-logo/1395994.png"},"vacancies_url":"https://api.hh.ru/vacancies?employer_id=1626408&host=hh.ru","trusted":true},"published_at":"2022-12-23T18:59:37+0300","created_at":"2022-12-23T18:59:37+0300","initial_created_at":"2022-11-29T18:59:37+0300","negotiations_url":null,"suitable_resumes_url":null,"apply_alternate_url":"https://hh.ru/applicant/vacancy_response?vacancyId=73097189","has_test":false,"test":null,"alternate_url":"https://hh.ru/vacancy/73097189","working_days":[],"working_time_intervals":[],"working_time_modes":[],"accept_temporary":false,"languages":[]}