{"id":"72701039","premium":false,"billing_type":{"id":"standard","name":"Стандарт"},"relations":[],"name":"C# Unity Developer","insider_interview":null,"response_letter_required":false,"area":{"id":"2","name":"Санкт-Петербург","url":"https://api.hh.ru/areas/2?host=hh.ru"},"salary":null,"type":{"id":"open","name":"Открытая"},"address":null,"allow_messages":true,"experience":{"id":"between3And6","name":"От 3 до 6 лет"},"schedule":{"id":"remote","name":"Удаленная работа"},"employment":{"id":"full","name":"Полная занятость"},"department":null,"contacts":null,"description":"<p>Известная Студия-разработчик и издатель игр <strong> </strong>ищет себе в команду <strong>C# Unity Developer</strong>.</p> <p>Мы предлагаем работу над проектом-флагманом нашей студии, находящемся на этапе активной разработки. Вы сможете принять участие в создании одной из лучших ПК игр, разрабатываемых на территории СНГ. Вас ждет дружный коллектив, помешанный на оружии и видеоиграх, уютный офис в центре города (или гибридный формат), гибкая разработка с активным шарингом знаний.</p> <ul> <li> <p><strong>Обязанности:</strong></p> <ul> <li> <p>Взаимодействие с тестировщиками, художниками, дизайнерами и другими разработчиками;</p> </li> <li> <p>Написание масштабируемого и читаемого кода с использованием современных методологий разработки (SOLID, KISS, DRY);</p> </li> <li> <p>Участие в разработке архитектуры проекта;</p> </li> <li> <p>Вёрстка и написание логики UI;</p> </li> <li> <p>Написание игровой логики, клиент-серверного взаимодействия;</p> </li> <li> <p>Участие в код-ревью;</p> </li> <li> <p>Оптимизация существующего кода.</p> </li> </ul> <p><strong>Требования:</strong></p> <ul> <li> <p>Отличное понимание C#, Unity;</p> </li> <li> <p>Уверенное понимание принципов ООП, паттернов проектирования и разработки;</p> </li> <li> <p>Опыт работы в Unity от 3-х лет;</p> </li> <li> <p>Опыт коммерческой разработки игр, наличие завершенных проектов;</p> </li> <li> <p>Наличие опыта работы с сетью, UGUI, понимание принципов работы асинхронного кода;</p> </li> <li> <p>Опыт профилирования и оптимизации всего игрового цикла, работа с GC;</p> </li> <li> <p>Владение системами контроля версий (Git).</p> </li> </ul> <p> </p> <p><strong>Будет преимуществом:</strong></p> <ul> <li> <p>Опыт оптимизации приложений (память, CPU, GPU, GC).</p> </li> </ul> <p> </p> <p><strong>Условия:</strong></p> <ul> <li> <p>Полностью &quot;белое&quot; оформление согласно ТК РФ, бонусы;</p> </li> <li> <p>Удобный график работы, который можно подстраивать под себя;</p> </li> <li> <p><strong>Удаленный формат</strong> или уютный комфортабельный офис в центре Санкт-Петербурга в 500 метрах от метро;</p> </li> <li> <p>Возможность работать удаленно;</p> </li> <li> <p>Комната отдыха с приставками, тренажерный зал, настольный теннис, душ,<br />кухня, чай, кофе и тд;</p> </li> <li> <p>ДМС после прохождения испытательного срока;</p> </li> <li> <p>Компенсация питания;</p> </li> <li> <p>Современное, мощное железо;</p> </li> <li> <p>Минимум бюрократии;</p> </li> <li> <p>Профессиональный и карьерный рост;</p> </li> <li> <p>Работа в профессиональной команде с большим опытом;</p> </li> <li> <p>Помощь при переезде из других регионов.</p> </li> </ul> </li> </ul>","branded_description":null,"vacancy_constructor_template":null,"key_skills":[{"name":"Git"},{"name":"ООП"},{"name":"Unity"},{"name":"C#"}],"accept_handicapped":false,"accept_kids":false,"archived":false,"response_url":null,"specializations":[{"id":"1.221","name":"Программирование, Разработка","profarea_id":"1","profarea_name":"Информационные технологии, интернет, телеком"},{"id":"1.50","name":"Системы управления предприятием (ERP)","profarea_id":"1","profarea_name":"Информационные технологии, интернет, телеком"},{"id":"1.82","name":"Инженер","profarea_id":"1","profarea_name":"Информационные технологии, интернет, телеком"},{"id":"1.9","name":"Web инженер","profarea_id":"1","profarea_name":"Информационные технологии, интернет, телеком"},{"id":"1.10","name":"Web мастер","profarea_id":"1","profarea_name":"Информационные технологии, интернет, телеком"}],"professional_roles":[{"id":"96","name":"Программист, разработчик"}],"code":null,"hidden":false,"quick_responses_allowed":false,"driver_license_types":[],"accept_incomplete_resumes":false,"employer":{"id":"4456441","name":"Hunt For You","url":"https://api.hh.ru/employers/4456441?host=hh.ru","alternate_url":"https://hh.ru/employer/4456441","logo_urls":{"original":"https://hhcdn.ru/employer-logo-original/709944.jpeg","90":"https://hhcdn.ru/employer-logo/3280892.jpeg","240":"https://hhcdn.ru/employer-logo/3280893.jpeg"},"vacancies_url":"https://api.hh.ru/vacancies?employer_id=4456441&host=hh.ru","trusted":true},"published_at":"2022-12-19T22:04:38+0300","created_at":"2022-12-19T22:04:38+0300","initial_created_at":"2022-11-21T18:42:07+0300","negotiations_url":null,"suitable_resumes_url":null,"apply_alternate_url":"https://hh.ru/applicant/vacancy_response?vacancyId=72701039","has_test":false,"test":null,"alternate_url":"https://hh.ru/vacancy/72701039","working_days":[],"working_time_intervals":[],"working_time_modes":[],"accept_temporary":false,"languages":[]}